lux_dex/__init__.py
lux_dex/client.py
lux_dex/exceptions.py
lux_dex/market_data.py
lux_dex/types.py
lux_dex-1.2.1.dist-info/METADATA
lux_dex-1.2.1.dist-info/WHEEL
lux_dex-1.2.1.dist-info/top_level.txt
lux_dex-1.2.1.dist-info/RECORD
